{
  "game_id": "game-006",
  "date": "2025-07-13T10:30:00Z",
  "game_type": "TextSummarization",
  "participants": ["TestModel-Alpha", "TestModel-Beta", "TestModel-Gamma", "TestModel-Delta"],
  "ranks": [1, 0, 3, 2],
  "scores": [92, 95, 78, 85],
  "description": "A challenge to accurately summarize long academic papers while preserving key information.",
  "additional_info": {
    "challenge_prompt": "Summarize the provided academic papers in 250 words or less while preserving all key findings and methodologies.",
    "papers": ["Quantum Computing Advances", "Climate Change Mitigation", "Neural Network Architectures"],
    "relevance_score": {
      "TestModel-Alpha": 0.92,
      "TestModel-Beta": 0.95,
      "TestModel-Gamma": 0.78,
      "TestModel-Delta": 0.85
    },
    "conciseness_score": {
      "TestModel-Alpha": 0.94,
      "TestModel-Beta": 0.96,
      "TestModel-Gamma": 0.81,
      "TestModel-Delta": 0.87
    },
    "word_count": {
      "TestModel-Alpha": 243,
      "TestModel-Beta": 235,
      "TestModel-Gamma": 268,
      "TestModel-Delta": 251
    }
  }
}
